setup.cfg
setup.py
./__init__.py
./configuration.py
./configuration.xml
./gateway.py
./gateway.xml
./gift_card.odt
./gift_card.py
./gift_card.xml
./product.py
./product.xml
./sale.py
./sale.xml
./tryton.cfg
./emails/gift_card_html.html
./emails/gift_card_text.html
./locale/de_DE.po
./tests/__init__.py
./tests/test_base.py
./tests/test_gift_card.py
./tests/test_views_depends.py
./view/configuration_form.xml
./view/gift_card_form.xml
./view/gift_card_price_form.xml
./view/gift_card_price_tree.xml
./view/gift_card_tree.xml
./view/product_form.xml
./view/redeem_done_form.xml
./view/redeem_start_form.xml
./view/sale_configuration_form.xml
./view/sale_form.xml
./view/sale_line_form.xml
./view/sale_payment_add_form.xml
./view/sale_payment_form.xml
./view/transaction_form.xml
fio_gift_card.egg-info/PKG-INFO
fio_gift_card.egg-info/SOURCES.txt
fio_gift_card.egg-info/dependency_links.txt
fio_gift_card.egg-info/entry_points.txt
fio_gift_card.egg-info/not-zip-safe
fio_gift_card.egg-info/requires.txt
fio_gift_card.egg-info/top_level.txt